README.rst
setup.py
timemon/__init__.py
timemon/compat.py
timemon/timemon.py
timemon.egg-info/PKG-INFO
timemon.egg-info/SOURCES.txt
timemon.egg-info/dependency_links.txt
timemon.egg-info/entry_points.txt
timemon.egg-info/not-zip-safe
timemon.egg-info/requires.txt
timemon.egg-info/top_level.txt
timemon/tests/__init__.py
timemon/tests/dummy.py
timemon/tests/timemon_test.py