Metadata-Version: 1.1
Name: timemon
Version: 1.0.0.dev0
Summary: timemon plugin for supervisord
Home-page: http://supervisord.org
Author: Andrii Kostenko
Author-email: andrey@kostenko.name
License: BSD-derived (http://www.repoze.org/LICENSE.txt)
Keywords: supervisor monitoring
Platform: UNKNOWN
Classifier: Development Status :: 3 - Alpha
Classifier: Environment :: No Input/Output (Daemon)
Classifier: Intended Audience :: System Administrators
Classifier: Natural Language :: English
Classifier: Operating System :: POSIX
Classifier: Programming Language :: Python :: 2
Classifier: Programming Language :: Python :: 2.6
Classifier: Programming Language :: Python :: 2.7
Classifier: Programming Language :: Python :: 3
Classifier: Programming Language :: Python :: 3.2
Classifier: Programming Language :: Python :: 3.3
Classifier: Programming Language :: Python :: 3.4
Classifier: Topic :: System :: Boot
Classifier: Topic :: System :: Monitoring
Classifier: Topic :: System :: Systems Administration
